langchain_opentutorial/__init__.py
langchain_opentutorial/env.py
langchain_opentutorial/evaluator.py
langchain_opentutorial/graphs.py
langchain_opentutorial/messages.py
langchain_opentutorial/package.py
langchain_opentutorial/document_loaders/__init__.py
langchain_opentutorial/document_loaders/hwp.py
langchain_opentutorial/document_loaders/pdf.py
langchain_opentutorial/rag/__init__.py
langchain_opentutorial/rag/base.py
langchain_opentutorial/rag/pdf.py
langchain_opentutorial/rag/utils.py
langchain_opentutorial/tools/__init__.py
langchain_opentutorial/tools/news.py
langchain_opentutorial/tools/tavily.py
langchain_opentutorial-0.0.7.dist-info/METADATA
langchain_opentutorial-0.0.7.dist-info/WHEEL
langchain_opentutorial-0.0.7.dist-info/top_level.txt
langchain_opentutorial-0.0.7.dist-info/RECORD
