Metadata-Version: 2.1
Name: langchain_opentutorial
Version: 0.0.7
Summary: LangChain-OpenTutorial(https://github.com/LangChain-OpenTutorial/LangChain-OpenTutorial) Packages
Home-page: https://github.com/LangChain-OpenTutorial/langchain-opentutorial-pypi
Author: LangChain-OpenTutorial
Author-email: langchain.opentutorial@gmail.com
Classifier: Programming Language :: Python :: 3
Classifier: License :: OSI Approved :: MIT License
Classifier: Operating System :: OS Independent
Requires-Python: >=3.6
Requires-Dist: requests
